[
  {
    "id": 1,
    "location": "Whitechapel Rd.",
    "city": "Tulare County, Los Angeles, CA 23415",
    "price": "$1,456,654.00",
    "image": "https://i.ibb.co.com/F8dc53x/Rectangle-42010.png",
    "category": "https://i.ibb.co.com/nfH1jCj/Frame-1321315997.png"
  },
  {
    "id": 2,
    "location": "Whitechapel Rd.",
    "city": "Tulare County, Los Angeles, CA 23415",
    "price": "$1,456,654.00",
    "image": "https://i.ibb.co.com/ry78BFG/Rectangle-42010-1.png",
    "category": "https://i.ibb.co.com/nfH1jCj/Frame-1321315997.png"
  },
  {
    "id": 3,
    "location": "Tulare County",
    "city": "Tulare County, Los Angeles, CA 23415",
    "price": "$1,456,654.00",
    "image": "https://i.ibb.co.com/98R9ZFB/Rectangle-42010-2.png",
    "category": "https://i.ibb.co.com/nfH1jCj/Frame-1321315997.png"
  },
  {
    "id": 4,
    "location": "Tulare County",
    "city": "Tulare County, Los Angeles, CA 23415",
    "price": "$1,456,654.00",
    "image": "https://i.ibb.co.com/GdVQ600/Rectangle-42010-3.png",
    "category": "https://i.ibb.co.com/nfH1jCj/Frame-1321315997.png"
  },
  {
    "id": 5,
    "location": "Tulare County",
    "city": "Tulare County, Los Angeles, CA 23415",
    "price": "$1,456,654.00",
    "image": "https://i.ibb.co.com/F8dc53x/Rectangle-42010.png",
    "category": "https://i.ibb.co.com/nfH1jCj/Frame-1321315997.png"
  },
  {
    "id": 6,
    "location": "Tulare County",
    "city": "Tulare County, Los Angeles, CA 23415",
    "price": "$1,456,654.00",
    "image": "https://i.ibb.co.com/F8dc53x/Rectangle-42010.png",
    "category": "https://i.ibb.co.com/nfH1jCj/Frame-1321315997.png"
  }
]
